opennn_pytorch/__init__.py
opennn_pytorch/__version__.py
opennn_pytorch/run.py
opennn_pytorch/algo/__init__.py
opennn_pytorch/algo/prediction.py
opennn_pytorch/algo/traintest.py
opennn_pytorch/dataset/__init__.py
opennn_pytorch/dataset/base.py
opennn_pytorch/dataset/custom.py
opennn_pytorch/decoder/__init__.py
opennn_pytorch/decoder/base.py
opennn_pytorch/decoder/decoder.py
opennn_pytorch/decoder/model.py
opennn_pytorch/encoder/__init__.py
opennn_pytorch/encoder/alexnet.py
opennn_pytorch/encoder/base.py
opennn_pytorch/encoder/googlenet.py
opennn_pytorch/encoder/lenet.py
opennn_pytorch/encoder/mobilenet.py
opennn_pytorch/encoder/resnet.py
opennn_pytorch/encoder/vgg.py
opennn_pytorch/loss/__init__.py
opennn_pytorch/loss/base.py
opennn_pytorch/loss/custom.py
opennn_pytorch/metric/__init__.py
opennn_pytorch/metric/base.py
opennn_pytorch/metric/sklearn_metric.py
opennn_pytorch/optimizer/__init__.py
opennn_pytorch/optimizer/base.py
opennn_pytorch/scheduler/__init__.py
opennn_pytorch/scheduler/base.py
opennn_pytorch/scheduler/custom.py
opennn_pytorch-1.1.3.dist-info/LICENSE
opennn_pytorch-1.1.3.dist-info/LICENSE.txt
opennn_pytorch-1.1.3.dist-info/METADATA
opennn_pytorch-1.1.3.dist-info/WHEEL
opennn_pytorch-1.1.3.dist-info/top_level.txt
opennn_pytorch-1.1.3.dist-info/RECORD
