Metadata-Version: 2.1
Name: opennn-pytorch
Version: 1.1.3
Summary: Neural Networks library for image classification task.
Home-page: https://github.com/Pe4enIks/OpenNN
Author: Evgenii Pishchik
Author-email: evgeniipishchik@mail.ru
License: MIT
Download-URL: https://github.com/Pe4enIks/OpenNN/archive/refs/tags/v1.1.3.tar.gz
Platform: UNKNOWN
Classifier: License :: OSI Approved :: MIT License
Classifier: Programming Language :: Python
Classifier: Programming Language :: Python :: 3
Classifier: Programming Language :: Python :: 3.9
Requires-Python: >=3.9.0
License-File: LICENSE
License-File: LICENSE.txt
Requires-Dist: torchvision (>=0.5.0)
Requires-Dist: matplotlib (>=3.0.0)
Requires-Dist: numpy (>=1.16.0)
Requires-Dist: tqdm (>=4.20.0)
Requires-Dist: pillow
Requires-Dist: sklearn
Requires-Dist: wandb
